LICENSE
README.md
setup.cfg
setup.py
Topsis_Arhanjit_102003116/102003116.py
Topsis_Arhanjit_102003116.egg-info/PKG-INFO
Topsis_Arhanjit_102003116.egg-info/SOURCES.txt
Topsis_Arhanjit_102003116.egg-info/dependency_links.txt
Topsis_Arhanjit_102003116.egg-info/entry_points.txt
Topsis_Arhanjit_102003116.egg-info/requires.txt
Topsis_Arhanjit_102003116.egg-info/top_level.txt