Metadata-Version: 2.1
Name: Topsis-Arhanjit-102003116
Version: 1.0.7
Summary: This is a Python library for handling problems related to Multiple Criteria Decision Making(MCDM)
Home-page: https://github.com/Arhan2002/Topsis-Arhanjit-102003116.git
Author: Arhanjit Sodhi
Author-email: arhanjitsodhi@gmail.com
License: MIT
Classifier: License :: OSI Approved :: MIT License
Classifier: Programming Language :: Python :: 3.6
Classifier: Programming Language :: Python :: 3.7
Classifier: Programming Language :: Python :: 3.8
License-File: LICENSE
